[
  {
    "name": "att",
    "value": "1-weqrDSk0uAaMUERCu8dUbZs6Whdu1yDuL7M2GZci",
    "domain": ".twitter.com",
    "path": "/",
    "expires": 1648662201.171018,
    "size": 45,
    "httpOnly": true,
    "secure": true,
    "session": false,
    "sameSite": "None",
    "sameParty": false,
    "sourceScheme": "Secure",
    "sourcePort": 443
  },
  {
    "name": "auth_token",
    "value": "c5c4f0dfe489c12680fefb73d7fefb9b77640522",
    "domain": ".twitter.com",
    "path": "/",
    "expires": 1806255800.195022,
    "size": 50,
    "httpOnly": true,
    "secure": true,
    "session": false,
    "sameSite": "None",
    "sameParty": false,
    "sourceScheme": "Secure",
    "sourcePort": 443
  },
  {
    "name": "ct0",
    "value": "245abf17f2f1a118f94ac8ef4797abf30dfc6df99b783eef32cf446433fb4e95112b431ed434f6e1004e7d6a44520c38bb93f65474646fd08180ced0faffad08abdf7dd04410d45527ee1b44ec6a0369",
    "domain": ".twitter.com",
    "path": "/",
    "expires": 1806255800.690201,
    "size": 163,
    "httpOnly": false,
    "secure": true,
    "session": false,
    "sameSite": "Lax",
    "sameParty": false,
    "sourceScheme": "Secure",
    "sourcePort": 443
  },
  {
    "name": "gt",
    "value": "1508862087434440706",
    "domain": ".twitter.com",
    "path": "/",
    "expires": 1648586528.673841,
    "size": 21,
    "httpOnly": false,
    "secure": true,
    "session": false,
    "sameParty": false,
    "sourceScheme": "Secure",
    "sourcePort": 443
  },
  {
    "name": "_ga",
    "value": "GA1.2.1338905631.1648575731",
    "domain": ".twitter.com",
    "path": "/",
    "expires": 1711647730,
    "size": 30,
    "httpOnly": false,
    "secure": false,
    "session": false,
    "sameParty": false,
    "sourceScheme": "Secure",
    "sourcePort": 443
  },
  {
    "name": "kdt",
    "value": "q4umLIxAJzPfUJVUyDeJoIdt92NX2Vn6irzmM43z",
    "domain": ".twitter.com",
    "path": "/",
    "expires": 1695836600.194913,
    "size": 43,
    "httpOnly": true,
    "secure": true,
    "session": false,
    "sameParty": false,
    "sourceScheme": "Secure",
    "sourcePort": 443
  },
  {
    "name": "_gid",
    "value": "GA1.2.1812143110.1648575731",
    "domain": ".twitter.com",
    "path": "/",
    "expires": 1648662130,
    "size": 31,
    "httpOnly": false,
    "secure": false,
    "session": false,
    "sameParty": false,
    "sourceScheme": "Secure",
    "sourcePort": 443
  },
  {
    "name": "personalization_id",
    "value": "\"v1_7qgLdAiJKGIIJ9RjhtrOrQ==\"",
    "domain": ".twitter.com",
    "path": "/",
    "expires": 1711647723.93817,
    "size": 47,
    "httpOnly": false,
    "secure": true,
    "session": false,
    "sameSite": "None",
    "sameParty": false,
    "sourceScheme": "Secure",
    "sourcePort": 443
  },
  {
    "name": "twid",
    "value": "u%3D1505949826252689408",
    "domain": ".twitter.com",
    "path": "/",
    "expires": 1680111800.939206,
    "size": 27,
    "httpOnly": false,
    "secure": true,
    "session": false,
    "sameSite": "None",
    "sameParty": false,
    "sourceScheme": "Secure",
    "sourcePort": 443
  },
  {
    "name": "guest_id",
    "value": "v1%3A164857572483806802",
    "domain": ".twitter.com",
    "path": "/",
    "expires": 1711647723.938188,
    "size": 31,
    "httpOnly": false,
    "secure": true,
    "session": false,
    "sameSite": "None",
    "sameParty": false,
    "sourceScheme": "Secure",
    "sourcePort": 443
  },
  {
    "name": "guest_id_ads",
    "value": "v1%3A164857572483806802",
    "domain": ".twitter.com",
    "path": "/",
    "expires": 1711647723.938149,
    "size": 35,
    "httpOnly": false,
    "secure": true,
    "session": false,
    "sameSite": "None",
    "sameParty": false,
    "sourceScheme": "Secure",
    "sourcePort": 443
  },
  {
    "name": "_twitter_sess",
    "value": "BAh7CSIKZmxhc2hJQzonQWN0aW9uQ29udHJvbGxlcjo6Rmxhc2g6OkZsYXNo%250ASGFzaHsABjoKQHVzZWR7ADoPY3JlYXRlZF9hdGwrCA5VxdZ%252FAToMY3NyZl9p%250AZCIlZDEwYjNmZWM2MTlmNjRiZTBlZWNlZDIwN2RiZWNlNTI6B2lkIiU3ZjFi%250AMDY1YWViZDM2MDFkMTNiYmU3OGY3N2Q3YmM1Yg%253D%253D--12fe2bb9637e51bcdf36cba773395c49f1220722",
    "domain": ".twitter.com",
    "path": "/",
    "expires": -1,
    "size": 302,
    "httpOnly": true,
    "secure": true,
    "session": true,
    "sameParty": false,
    "sourceScheme": "Secure",
    "sourcePort": 443
  },
  {
    "name": "guest_id_marketing",
    "value": "v1%3A164857572483806802",
    "domain": ".twitter.com",
    "path": "/",
    "expires": 1711647723.937988,
    "size": 41,
    "httpOnly": false,
    "secure": true,
    "session": false,
    "sameSite": "None",
    "sameParty": false,
    "sourceScheme": "Secure",
    "sourcePort": 443
  }
]