[
  {
    "name": "d_prefs",
    "value": "MToxLGNvbnNlbnRfdmVyc2lvbjoyLHRleHRfdmVyc2lvbjoxMDAw",
    "domain": ".twitter.com",
    "path": "/",
    "expires": 1664127693.043128,
    "size": 59,
    "httpOnly": false,
    "secure": true,
    "session": false,
    "sameParty": false,
    "sourceScheme": "Secure",
    "sourcePort": 443
  },
  {
    "name": "att",
    "value": "1-q0ntwFBeWx5P2MLfBNx1AwnXI9mkjvsn3afG68RF",
    "domain": ".twitter.com",
    "path": "/",
    "expires": 1648662084.080459,
    "size": 45,
    "httpOnly": true,
    "secure": true,
    "session": false,
    "sameSite": "None",
    "sameParty": false,
    "sourceScheme": "Secure",
    "sourcePort": 443
  },
  {
    "name": "twid",
    "value": "u%3D1505943758239682566",
    "domain": ".twitter.com",
    "path": "/",
    "expires": 1680111683.894951,
    "size": 27,
    "httpOnly": false,
    "secure": true,
    "session": false,
    "sameSite": "None",
    "sameParty": false,
    "sourceScheme": "Secure",
    "sourcePort": 443
  },
  {
    "name": "ct0",
    "value": "3a91e8789c0d3d91a633335aa42dacbb423a298dff90ccc8d00a80c15c1dc96b664a8e11952662ac34b6f80b7e36f4533fd18e9046b3891a3bff85e1e33b9462b8ab2b8568e74fdf50c61a2149eeba0f",
    "domain": ".twitter.com",
    "path": "/",
    "expires": 1682790083.608312,
    "size": 163,
    "httpOnly": false,
    "secure": true,
    "session": false,
    "sameSite": "Lax",
    "sameParty": false,
    "sourceScheme": "Secure",
    "sourcePort": 443
  },
  {
    "name": "auth_token",
    "value": "8fea7e9bf8aeffbefc42cc94c1a48d243ad8dd47",
    "domain": ".twitter.com",
    "path": "/",
    "expires": 1682790083.336636,
    "size": 50,
    "httpOnly": true,
    "secure": true,
    "session": false,
    "sameSite": "None",
    "sameParty": false,
    "sourceScheme": "Secure",
    "sourcePort": 443
  },
  {
    "name": "_twitter_sess",
    "value": "BAh7CSIKZmxhc2hJQzonQWN0aW9uQ29udHJvbGxlcjo6Rmxhc2g6OkZsYXNo%250ASGFzaHsABjoKQHVzZWR7ADoPY3JlYXRlZF9hdGwrCAJpw9Z%252FAToMY3NyZl9p%250AZCIlNWZjNTQ2MGY0NjE5ZWFhYWMxNzMwYzllNTRkMmUwYmQ6B2lkIiVhODI5%250AYWU4YzIzNzcyNGM4YzQ2ZjUyNGYzZjA3Y2M0MQ%253D%253D--e443d9feaa288209a144f9d5e9ee6e08da0e71d1",
    "domain": ".twitter.com",
    "path": "/",
    "expires": -1,
    "size": 302,
    "httpOnly": true,
    "secure": true,
    "session": true,
    "sameParty": false,
    "sourceScheme": "Secure",
    "sourcePort": 443
  },
  {
    "name": "kdt",
    "value": "12IFmCfq5rGzW5Xo5gqHeISiL5YAZ2MGplV0qmod",
    "domain": ".twitter.com",
    "path": "/",
    "expires": 1682790083.336537,
    "size": 43,
    "httpOnly": true,
    "secure": true,
    "session": false,
    "sameParty": false,
    "sourceScheme": "Secure",
    "sourcePort": 443
  },
  {
    "name": "gt",
    "value": "1508861560344637441",
    "domain": ".twitter.com",
    "path": "/",
    "expires": 1648586403.00027,
    "size": 21,
    "httpOnly": false,
    "secure": true,
    "session": false,
    "sameParty": false,
    "sourceScheme": "Secure",
    "sourcePort": 443
  },
  {
    "name": "guest_id",
    "value": "v1%3A164857559993071837",
    "domain": ".twitter.com",
    "path": "/",
    "expires": 1682789999.026579,
    "size": 31,
    "httpOnly": false,
    "secure": true,
    "session": false,
    "sameSite": "None",
    "sameParty": false,
    "sourceScheme": "Secure",
    "sourcePort": 443
  }
]